flake8_import_order_tbm/__about__.py
flake8_import_order_tbm/__init__.py
flake8_import_order_tbm/style.py
flake8_import_order_tbm-1.3.0.dist-info/entry_points.txt
flake8_import_order_tbm-1.3.0.dist-info/LICENSE
flake8_import_order_tbm-1.3.0.dist-info/WHEEL
flake8_import_order_tbm-1.3.0.dist-info/METADATA
flake8_import_order_tbm-1.3.0.dist-info/RECORD
