Metadata-Version: 2.1
Name: flake8-import-order-tbm
Version: 1.3.0
Summary: flake8-import-order style plugin for my (thebigmunch) taste.
Home-page: https://github.com/thebigmunch/flake8-import-order-tbm
License: MIT
Author: thebigmunch
Author-email: mail@thebigmunch.me
Requires-Python: >=3.6,<4.0
Classifier: License :: OSI Approved :: MIT License
Classifier: Programming Language :: Python :: 3
Classifier: Programming Language :: Python :: 3.6
Classifier: Programming Language :: Python :: 3.7
Classifier: Programming Language :: Python :: 3.8
Provides-Extra: dev
Provides-Extra: lint
Requires-Dist: flake8 (>=3.5,<4.0); extra == "dev" or extra == "lint"
Requires-Dist: flake8-builtins (>=1.0,<2.0); extra == "dev" or extra == "lint"
Requires-Dist: flake8-comprehensions (>=2.0,<=4.0); extra == "dev" or extra == "lint"
Requires-Dist: flake8-import-order (>=0.18,<0.19); extra == "dev" or extra == "lint"
Requires-Dist: flake8-import-order-tbm (>=1.0,<2.0); extra == "dev" or extra == "lint"
Requires-Dist: natsort (>=5.0,<8.0)
Requires-Dist: nox (>=2019,<2020); extra == "dev"
Project-URL: Repository, https://github.com/thebigmunch/flake8-import-order-tbm
